round_nutrition/__init__.py
round_nutrition/general.py
round_nutrition/mineral.py
round_nutrition/other.py
round_nutrition/util.py
round_nutrition/vitamin.py
round_nutrition-1.1.1.dist-info/LICENSE
round_nutrition-1.1.1.dist-info/METADATA
round_nutrition-1.1.1.dist-info/WHEEL
round_nutrition-1.1.1.dist-info/top_level.txt
round_nutrition-1.1.1.dist-info/RECORD
