Metadata-Version: 2.1
Name: round-nutrition
Version: 1.1.1
Summary: Round nutritional values for federal compliance
Author-email: Harsh Dadhich <me@harshdadhich.com>
License: MIT
Project-URL: Source, https://github.com/hdadhich01/round-nutrition
Keywords: round,nutrition,fda
Classifier: License :: OSI Approved :: MIT License
Classifier: Programming Language :: Python
Classifier: Programming Language :: Python :: 3
Classifier: Topic :: Scientific/Engineering :: Bio-Informatics
Classifier: Topic :: Scientific/Engineering :: Chemistry
Classifier: Topic :: Scientific/Engineering :: Visualization
Classifier: Topic :: Software Development :: User Interfaces
Classifier: Topic :: Utilities
License-File: LICENSE
